missav_toolbox/__init__.py
missav_toolbox/base_downloader.py
missav_toolbox/missav_cover.py
missav_toolbox/missav_video.py
missav_toolbox/type_enum.py
missav_toolbox/assets/SmileySans-Oblique.ttf
missav_toolbox/assets/monthly.png
missav_toolbox/assets/new_release.png
missav_toolbox/assets/recent_update.png
missav_toolbox/assets/today.png
missav_toolbox/assets/weekly.png
missav_toolbox-1.1.0.dist-info/LICENSE
missav_toolbox-1.1.0.dist-info/METADATA
missav_toolbox-1.1.0.dist-info/WHEEL
missav_toolbox-1.1.0.dist-info/top_level.txt
missav_toolbox-1.1.0.dist-info/RECORD
