Metadata-Version: 2.1
Name: missav_toolbox
Version: 1.1.0
Home-page: https://github.com/1bananachicken/MissAV-Toolbox
Author: bananachicken
Classifier: Programming Language :: Python :: 3
Classifier: License :: OSI Approved :: GNU General Public License v3 (GPLv3)
Classifier: Operating System :: OS Independent
License-File: LICENSE
Requires-Dist: requests
Requires-Dist: cloudscraper
Requires-Dist: Pillow
Requires-Dist: bs4
Requires-Dist: m3u8
Requires-Dist: natsort
Requires-Dist: ffmpeg-python
